Metadata-Version: 1.0
Name: ez-distributions
Version: 1.0
Summary: Gaussian and Binomial distributions
Home-page: UNKNOWN
Author: Giorgos Moysiadis
Author-email: UNKNOWN
License: UNKNOWN
Platform: UNKNOWN
